README.md
setup.cfg
setup.py
eventdetector/__init__.py
eventdetector/annotate.py
eventdetector/utils.py
eventdetector.egg-info/PKG-INFO
eventdetector.egg-info/SOURCES.txt
eventdetector.egg-info/dependency_links.txt
eventdetector.egg-info/requires.txt
eventdetector.egg-info/top_level.txt
scripts/event-detector