Metadata-Version: 1.1
Name: eventdetector
Version: 0.9
Summary: Deep Learning models for automatic gait event annotation
Home-page: http://github.com/kidzik/event-detector
Author: Lukasz Kidzinski
Author-email: lukasz.kidzinski@gmail.com
License: Apache 2.0
Platform: UNKNOWN
Classifier: Intended Audience :: Science/Research
Classifier: Operating System :: OS Independent
Classifier: Programming Language :: Python :: 2.7
Classifier: Topic :: Scientific/Engineering :: Artificial Intelligence
